envyamlconverter/__init__.py
envyamlconverter-0.1.dist-info/METADATA
envyamlconverter-0.1.dist-info/WHEEL
envyamlconverter-0.1.dist-info/top_level.txt
envyamlconverter-0.1.dist-info/RECORD
