Metadata-Version: 2.1
Name: envyamlconverter
Version: 0.1
Summary: Env Yaml Converter
Home-page: https://github.com/asrvstv5/envToDeploymentYaml
Author: Amitesh Srivastava
Author-email: asrvstv5@gmail.com
License: MIT
Platform: UNKNOWN
